Metadata-Version: 2.1
Name: droot
Version: 1.0.2
Summary: Description of your package
Author: hanbuhuai
Author-email: 2578187302@qq.com
License: MIT
